llm_blocks/__init__.py
llm_blocks/block_factory.py
llm_blocks/blocks.py
llm_blocks/chat_utils.py
llm_blocks-0.3.7.dist-info/METADATA
llm_blocks-0.3.7.dist-info/WHEEL
llm_blocks-0.3.7.dist-info/top_level.txt
llm_blocks-0.3.7.dist-info/RECORD
