Metadata-Version: 2.1
Name: llm-blocks
Version: 0.3.7
Summary: Simple interface for creating and managing LLM chains
Home-page: https://github.com/voynow/llm-blocks
Author: Jamie Voynow
Author-email: voynow99@gmail.com
Classifier: Programming Language :: Python :: 3
Classifier: License :: OSI Approved :: MIT License
Classifier: Operating System :: OS Independent
Requires-Python: >=3.6
Requires-Dist: python-dotenv
Requires-Dist: openai
